odoo/addons/mrp_subcontracting_purchase_link/README.rst
odoo/addons/mrp_subcontracting_purchase_link/__init__.py
odoo/addons/mrp_subcontracting_purchase_link/__manifest__.py
odoo/addons/mrp_subcontracting_purchase_link/hooks.py
odoo/addons/mrp_subcontracting_purchase_link/i18n/it.po
odoo/addons/mrp_subcontracting_purchase_link/i18n/ja.po
odoo/addons/mrp_subcontracting_purchase_link/i18n/mrp_subcontracting_purchase_link.pot
odoo/addons/mrp_subcontracting_purchase_link/migrations/14.0.2.0.0/post-migration.py
odoo/addons/mrp_subcontracting_purchase_link/models/__init__.py
odoo/addons/mrp_subcontracting_purchase_link/models/mrp_production.py
odoo/addons/mrp_subcontracting_purchase_link/models/purchase_order.py
odoo/addons/mrp_subcontracting_purchase_link/models/stock_picking.py
odoo/addons/mrp_subcontracting_purchase_link/readme/CONTRIBUTORS.rst
odoo/addons/mrp_subcontracting_purchase_link/readme/DESCRIPTION.rst
odoo/addons/mrp_subcontracting_purchase_link/static/description/icon.png
odoo/addons/mrp_subcontracting_purchase_link/static/description/index.html
odoo/addons/mrp_subcontracting_purchase_link/tests/__init__.py
odoo/addons/mrp_subcontracting_purchase_link/tests/test_mrp_subcontracting_purchase_link.py
odoo/addons/mrp_subcontracting_purchase_link/views/mrp_production_views.xml
odoo/addons/mrp_subcontracting_purchase_link/views/purchase_order_views.xml
odoo14_addon_mrp_subcontracting_purchase_link-14.0.2.1.0.dist-info/METADATA
odoo14_addon_mrp_subcontracting_purchase_link-14.0.2.1.0.dist-info/WHEEL
odoo14_addon_mrp_subcontracting_purchase_link-14.0.2.1.0.dist-info/top_level.txt
odoo14_addon_mrp_subcontracting_purchase_link-14.0.2.1.0.dist-info/RECORD
